{
	"add-field-type": [
        {
            "name": "textfield",
            "class": "solr.TextField",
            "indexAnalyzer": {
                "tokenizer": {
                    "class": "solr.StandardTokenizerFactory"
                },
                "filters": [
                    {"class": "solr.ASCIIFoldingFilterFactory", "preserveOriginal": true},
                    {"class": "solr.LowerCaseFilterFactory"}
                ]
            },
            "queryAnalyzer": {
                "tokenizer": {
                    "class": "solr.StandardTokenizerFactory"
                },
                "filters": [
                    {"class": "solr.ASCIIFoldingFilterFactory", "preserveOriginal": true},
                    {"class": "solr.LowerCaseFilterFactory"}
                ]
            }
        },
        {
            "name": "release_date",
            "class": "solr.DatePointField"
        },
        {
            "name": "meta_score",
            "class": "solr.IntPointField"
        },
        {
            "name": "user_review",
            "class": "solr.FloatPointField"
        },
        {
            "name": "reviews",
            "class": "solr.TextField"
        }
    ],
    "add-field": [
        {
            "name": "title",
            "type": "textfield",
            "indexed": true
        },
        {
            "name": "summary",
            "type": "textfield",
            "indexed": true
        },
        {
            "name": "wikipedia",
            "type": "textfield",
            "indexed": true
        },
        {
            "name": "genre",
            "type": "textfield",
            "indexed": true
        },
        {
            "name": "platform",
            "type": "textfield",
            "indexed": true
        },
        {
            "name": "release_date",
            "type": "release_date",
            "indexed": true
        },
        {
            "name": "meta_score",
            "type": "meta_score",
            "indexed": true
        },
        {
            "name": "user_review",
            "type": "user_review",
            "indexed": true
        },
        {
            "name": "reviewer",
            "type": "textfield",
            "indexed": true
        },
        {
            "name": "review",
            "type": "textfield",
            "indexed": true
        },
        {
            "name": "reviews",
            "type": "reviews",
            "indexed": true
        }
    ]
}
